NORDic/__init__.py
NORDic/NORDic_DR/__init__.py
NORDic/NORDic_DR/bandits.py
NORDic/NORDic_DR/functions.py
NORDic/NORDic_DR/utils.py
NORDic/NORDic_DS/__init__.py
NORDic/NORDic_DS/functions.py
NORDic/NORDic_DS/get_drug_signatures.py
NORDic/NORDic_DS/get_drug_targets.py
NORDic/NORDic_NI/__init__.py
NORDic/NORDic_NI/cytoscape_style.py
NORDic/NORDic_NI/functions.py
NORDic/NORDic_PMR/__init__.py
NORDic/NORDic_PMR/functions.py
NORDic/UTILS/DISGENET_utils.py
NORDic/UTILS/LINCS_utils.py
NORDic/UTILS/STRING_utils.py
NORDic/UTILS/__init__.py
NORDic/UTILS/utils_data.py
NORDic/UTILS/utils_exp.py
NORDic/UTILS/utils_grn.py
NORDic/UTILS/utils_network.py
NORDic/UTILS/utils_plot.py
NORDic/UTILS/utils_sim.py
NORDic/UTILS/utils_state.py
nordic-2.7.1.dist-info/METADATA
nordic-2.7.1.dist-info/WHEEL
nordic-2.7.1.dist-info/top_level.txt
nordic-2.7.1.dist-info/RECORD
