Metadata-Version: 2.4
Name: NORDic
Version: 2.7.1
Summary: Network Oriented Repurposing of Drugs (NORDic): network identification / master regulator detection / drug effect simulator / drug repurposing
Home-page: https://github.com/clreda/NORDic
Author: Clémence Réda
Author-email: clemence.reda@inserm.fr
Classifier: Intended Audience :: Science/Research
Classifier: Topic :: Scientific/Engineering
Classifier: Topic :: Scientific/Engineering :: Artificial Intelligence
Classifier: Topic :: Scientific/Engineering :: Bio-Informatics
Requires-Python: >=3.8.5
Requires-Dist: pandas>=1.5.1
Requires-Dist: numpy!=2.0.*,!=2.1.*,>=1.22.4
Requires-Dist: clingo>=5.6.1
Requires-Dist: graphviz>=0.20.1
Requires-Dist: bonesis>=0.4.91
Requires-Dist: mpbn>=2.0
Requires-Dist: matplotlib>=3.3.4
Requires-Dist: scikit_learn>=1.1.2
Requires-Dist: scipy>=1.6.2
Requires-Dist: qnorm>=0.5.1
Requires-Dist: tqdm>=4.62.3
Requires-Dist: cmapPy>=4.0.1
Requires-Dist: openpyxl>=3.0.10
Requires-Dist: quadprog>=0.1.11
Requires-Dist: seaborn>=0.12.1
Requires-Dist: omnipath>=1.0.6
Requires-Dist: maboss>=0.8.4
Dynamic: author
Dynamic: author-email
Dynamic: classifier
Dynamic: description
Dynamic: description-content-type
Dynamic: home-page
Dynamic: keywords
Dynamic: requires-dist
Dynamic: requires-python
Dynamic: summary
